{
  "type": "grouping",
  "neverRecomputeExistingPartitions": false,
  "optionalDependencies": false,
  "customMeta": {
    "kv": {}
  },
  "redispatchPartitioning": false,
  "maxRunningActivities": 0,
  "inputs": {
    "main": {
      "items": [
        {
          "ref": "dss_ml_by_templates_performance_prepared",
          "deps": []
        }
      ]
    }
  },
  "outputs": {
    "main": {
      "items": [
        {
          "ref": "dss_ml_by_templates_performance_by_original",
          "appendMode": false
        }
      ]
    }
  },
  "versionTag": {
    "versionNumber": 3,
    "lastModifiedBy": {
      "login": "leo.dreyfus"
    },
    "lastModifiedOn": 1574872300762
  },
  "creationTag": {
    "versionNumber": 0,
    "lastModifiedBy": {
      "login": "leo.dreyfus"
    },
    "lastModifiedOn": 1574872244084
  },
  "tags": [],
  "customFields": {},
  "checklists": {
    "checklists": []
  }
}